Metadata-Version: 2.4
Name: llama-index-readers-memos
Version: 0.4.1
Summary: llama-index readers memos integration
Author-email: Your Name <you@example.com>
Maintainer: bubu
License-Expression: MIT
License-File: LICENSE
Keywords: memos,note
Requires-Python: <4.0,>=3.9
Requires-Dist: llama-index-core<0.15,>=0.13.0
